zenoss.py
zenoss_fork-0.7.4.dist-info/DESCRIPTION.rst
zenoss_fork-0.7.4.dist-info/METADATA
zenoss_fork-0.7.4.dist-info/RECORD
zenoss_fork-0.7.4.dist-info/WHEEL
zenoss_fork-0.7.4.dist-info/metadata.json
zenoss_fork-0.7.4.dist-info/top_level.txt
