Metadata-Version: 2.0
Name: zenoss-fork
Version: 0.7.4
Summary: Module to work with the Zenoss JSON API (Fork)
Home-page: https://github.com/stevegoossens/python-zenoss
Author: Steve Goossens
Author-email: steve.goossens@bbc.co.uk
License: UNKNOWN
Keywords: zenoss,api,json,rest
Platform: UNKNOWN
